{
 "kpId": "kp-x3-05-002",
 "beats": [
  {
   "n": 1,
   "point": "热平衡:两个能交换热量的系统,经足够长时间后一切宏观性质不再变化,达到的共同稳定状态。",
   "check": "两个系统一接触就算达到热平衡吗?",
   "trap": "误以为接触就立即热平衡,忽略'经过足够长时间、宏观性质不再变化'的条件"
  },
  {
   "n": 2,
   "point": "判断两系统是否热平衡的唯一判据是温度相同:$T_A=T_B$ 即热平衡,温度不等则热量由高温传向低温。",
   "check": "判断两系统是否热平衡,看哪个物理量?",
   "trap": "拿压强、体积等其他参量当热平衡判据"
  },
  {
   "n": 3,
   "point": "热平衡定律(热力学第零定律):若 A 与 C 热平衡、B 也与 C 热平衡,则 A 与 B 必然热平衡。",
   "check": "A、B 分别与 C 热平衡,A 和 B 直接接触会有净热传递吗?"
  },
  {
   "n": 4,
   "point": "第零定律揭示互为热平衡的系统有一个共同宏观性质——温度,它是温度概念成立的逻辑基础。",
   "check": "第零定律说明一切互为热平衡的系统共有的宏观性质是什么?"
  },
  {
   "n": 5,
   "point": "温度计能测温靠第零定律:温度计分别与两物体接触达热平衡后读数相同,就说明两物体温度相同。",
   "check": "两个物体不直接接触,凭什么用温度计比较它们的温度?"
  },
  {
   "n": 6,
   "point": "热力学温标与摄氏温标换算:$T=t+273.15\\ \\mathrm{K}$,高考计算常近似取 $T=t+273\\ \\mathrm{K}$。",
   "check": "27 ℃ 对应多少开尔文?",
   "trap": "计算题里忘把摄氏温度换成热力学温度就代入状态方程"
  },
  {
   "n": 7,
   "point": "平衡态是一个系统内部各处状态参量均匀稳定;热平衡是两个系统之间温度相等的关系,二者不可混淆。",
   "check": "平衡态和热平衡,各是'几个系统'的事?",
   "trap": "把单系统的平衡态与系统间的热平衡混为一谈"
  },
  {
   "n": 8,
   "point": "热平衡只保证温度相同,两系统的压强、体积、密度、分子数密度都可以不同。",
   "check": "两气体达到热平衡,它们压强一定相等吗?",
   "trap": "由热平衡推出'一切状态参量都相同'"
  },
  {
   "n": 9,
   "point": "'热平衡时两系统具有相同热量'是错误说法:热量是过程量,系统不'含有'热量;热平衡也不代表内能相同。",
   "check": "能说两个热平衡的物体含有相同的热量吗?为什么?",
   "trap": "把热量当状态量,或由温度相同推出内能相同"
  }
 ]
}